[
  {
    "key": {
      "remoteJid": "254743518481@s.whatsapp.net",
      "fromMe": true,
      "id": "3EB0602CEC4909C1F3D72C"
    },
    "message": {
      "extendedTextMessage": {
        "text": ".menu",
        "contextInfo": {
          "disappearingMode": {
            "initiator": "CHANGED_IN_CHAT",
            "trigger": "CHAT_SETTING"
          }
        },
        "inviteLinkGroupTypeV2": "DEFAULT"
      }
    },
    "messageTimestamp": "1759500918",
    "status": "SERVER_ACK",
    "broadcast": false,
    "pushName": "404 Not Found"
  }
]