[
  {
    "key": {
      "remoteJid": "120363421377068688@g.us",
      "fromMe": false,
      "id": "AC630A8FE84F48B747196A9A8FD6FFC3",
      "participant": "258815249408132@lid"
    },
    "message": {
      "reactionMessage": {
        "key": {
          "remoteJid": "120363421377068688@g.us",
          "fromMe": false,
          "id": "ACBFF95DE354D47BBFF01BE4DD0A1850",
          "participant": "82644129808501@lid"
        },
        "text": "😂",
        "senderTimestampMs": "1759436524998"
      }
    },
    "messageTimestamp": "1759436525",
    "participant": "258815249408132@lid",
    "broadcast": false,
    "pushName": "CASCANTE"
  }
]