[
  {
    "key": {
      "remoteJid": "254762917014@s.whatsapp.net",
      "fromMe": true,
      "id": "AC2620C021F4D828807E1180BEED3B6B"
    },
    "message": {
      "protocolMessage": {
        "type": "PEER_DATA_OPERATION_REQUEST_RESPONSE_MESSAGE",
        "peerDataOperationRequestResponseMessage": {
          "peerDataOperationRequestType": "PLACEHOLDER_MESSAGE_RESEND",
          "stanzaId": "3EB042DCB7A75570592E79",
          "peerDataOperationResult": [
            {
              "mediaUploadResult": "NOT_FOUND"
            }
          ]
        }
      }
    },
    "messageTimestamp": "1759501046",
    "status": "SERVER_ACK",
    "broadcast": false
  }
]